string_builder/__init__.py
python_string_builder-1.0.1.dist-info/METADATA
python_string_builder-1.0.1.dist-info/WHEEL
python_string_builder-1.0.1.dist-info/top_level.txt
python_string_builder-1.0.1.dist-info/RECORD
